fusio/__init__.py
fusio/classes/__init__.py
fusio/classes/astra.py
fusio/classes/gacode.py
fusio/classes/imas.py
fusio/classes/io.py
fusio/classes/jintrac.py
fusio/classes/omas.py
fusio/classes/torax.py
fusio/utils/__init__.py
fusio/utils/eqdsk_tools.py
fusio/utils/json_tools.py
fusio/utils/plasma_tools.py
fusio-0.2.0.dist-info/licenses/LICENSE
fusio-0.2.0.dist-info/METADATA
fusio-0.2.0.dist-info/WHEEL
fusio-0.2.0.dist-info/top_level.txt
fusio-0.2.0.dist-info/RECORD
