Metadata-Version: 2.4
Name: fusio
Version: 0.2.0
Summary: Input file conversions to popular file formats in fusion research
Author-email: Aaron Ho <aaronkho@mit.edu>
License-Expression: MIT
Project-URL: Homepage, https://github.com/aaronkho/fusio
Keywords: fusion,interfaces
Classifier: Development Status :: 2 - Pre-Alpha
Classifier: Intended Audience :: Science/Research
Classifier: Topic :: Scientific/Engineering
Classifier: Topic :: Software Development :: User Interfaces
Classifier: Programming Language :: Python :: 3.10
Classifier: Programming Language :: Python :: 3.11
Classifier: Programming Language :: Python :: 3.12
Classifier: Programming Language :: Python :: 3 :: Only
Requires-Python: <3.13,>=3.10
License-File: LICENSE
Requires-Dist: typing-extensions; python_version < "3.11"
Requires-Dist: numpy
Requires-Dist: scipy
Requires-Dist: xarray
Requires-Dist: h5py
Requires-Dist: contourpy
Requires-Dist: shapely
Requires-Dist: imas-python[netcdf,xarray]
Requires-Dist: omas
Provides-Extra: dev
Requires-Dist: pytest; extra == "dev"
Requires-Dist: mypy; extra == "dev"
Requires-Dist: pylint; extra == "dev"
Provides-Extra: build
Requires-Dist: build; extra == "build"
Requires-Dist: twine; extra == "build"
Dynamic: license-file
